{
    "data": {
        "library": {
            "irwan@tokemedan.com": {
                "code": 200,
                "start_date": "December 11, 2019",
                "expiry": "October 5, 2999",
                "MultiDevice": 1,
                "uid": {
                    "FC56-A72A-B885-FF5E-36B4-C774-DAA7-FFBC": 1
                },
                "license_key": "A16690B62F71A3ED585F864CFC5E24E8",
                "email": "irwan@tokemedan.com"
            },
            "irwan@inspirasiprogrammer.id": {
                "code": 200,
                "start_date": "December 11, 2019",
                "expiry": "October 5, 2999",
                "MultiDevice": 1,
                "uid": {
                    "AF64D-0B4F-2814-0112-15ED-BF7F-277B-0AA3": 1
                },
                "license_key": "A16690B62F71A3ED585F864CFC5E24E8",
                "email": "irwan@inspirasiprogrammer.id"
            },
            "irwansyahputra92@gmail.com": {
                "code": 200,
                "start_date": "December 11, 2019",
                "expiry": "October 5, 2999",
                "MultiDevice": 1,
                "uid": {
                    "FC56-A72A-B885-FF5E-36B4-C774-DAA7-FFBC": 1,
                    "97CE-E6B7-7E21-F13F-B9B4-58D4-882D-5B38": 1
                },
                "license_key": "A16690B62F71A3ED585F864CFC5E24E8",
                "email": "irwansyahputra92@gmail.com"
            }
        }
    }
}
